CHANGES.rst
DESCRIPTION.rst
LICENSE
MANIFEST.in
README.md
setup.py
src/sdc/class_lister.py
src/sdc/core.py
src/sdc/help.py
src/sdc/registry.py
src/sdc/api/_2d.py
src/sdc/api/__init__.py
src/sdc/api/_cleaner.py
src/sdc/api/_data.py
src/sdc/api/_filter.py
src/sdc/api/_generator.py
src/sdc/api/_reader.py
src/sdc/api/_spectralio.py
src/sdc/api/_utils.py
src/sdc/api/_writer.py
src/sdc/cleaner/__init__.py
src/sdc/cleaner/_iqr.py
src/sdc/filter/__init__.py
src/sdc/filter/_abstractpls.py
src/sdc/filter/_add_sampledata.py
src/sdc/filter/_apply_cleaner.py
src/sdc/filter/_center.py
src/sdc/filter/_check_duplicate_filenames.py
src/sdc/filter/_discard_by_name.py
src/sdc/filter/_downsample.py
src/sdc/filter/_equi_distance.py
src/sdc/filter/_log.py
src/sdc/filter/_max_records.py
src/sdc/filter/_metadata.py
src/sdc/filter/_metadata_from_name.py
src/sdc/filter/_metadata_to_placeholder.py
src/sdc/filter/_passthrough.py
src/sdc/filter/_pca.py
src/sdc/filter/_pls1.py
src/sdc/filter/_pyfunc_filter.py
src/sdc/filter/_randomize_records.py
src/sdc/filter/_record_window.py
src/sdc/filter/_rename.py
src/sdc/filter/_rownorm.py
src/sdc/filter/_sample.py
src/sdc/filter/_savitzkygolay.py
src/sdc/filter/_savitzkygolay2.py
src/sdc/filter/_set_placeholder.py
src/sdc/filter/_simpls.py
src/sdc/filter/_spectrum_to_sampledata.py
src/sdc/filter/_split_records.py
src/sdc/filter/_standardize.py
src/sdc/filter/_tee.py
src/sdc/generator/__init__.py
src/sdc/generator/_dirs.py
src/sdc/generator/_list.py
src/sdc/generator/_null.py
src/sdc/generator/_range.py
src/sdc/reader/__init__.py
src/sdc/reader/_adams.py
src/sdc/reader/_arff.py
src/sdc/reader/_asc.py
src/sdc/reader/_asciixy.py
src/sdc/reader/_cal.py
src/sdc/reader/_csv.py
src/sdc/reader/_dpt.py
src/sdc/reader/_json.py
src/sdc/reader/_mps.py
src/sdc/reader/_multi.py
src/sdc/reader/_nir.py
src/sdc/reader/_opus.py
src/sdc/reader/_opus_ext.py
src/sdc/reader/_poll_dir.py
src/sdc/reader/_pyfunc.py
src/sdc/reader/_spa.py
src/sdc/reader/_zip.py
src/spectral_data_converter.egg-info/PKG-INFO
src/spectral_data_converter.egg-info/SOURCES.txt
src/spectral_data_converter.egg-info/dependency_links.txt
src/spectral_data_converter.egg-info/entry_points.txt
src/spectral_data_converter.egg-info/requires.txt
src/spectral_data_converter.egg-info/top_level.txt