Metadata-Version: 2.1
Name: spectral-data-converter
Version: 0.0.2
Summary: Python3 library for converting (and filtering) spectral data in various formats.
Home-page: https://github.com/waikato-datamining/spectral-data-converter
Author: Peter Reutemann
Author-email: fracpete@waikato.ac.nz
License: MIT License
Classifier: Development Status :: 4 - Beta
Classifier: License :: OSI Approved :: MIT License
Classifier: Topic :: Scientific/Engineering
License-File: LICENSE
